covidtracker/CovidTracker.py
covidtracker/__init__.py
covidtracker/calculate_stat_summary.py
covidtracker/get_covid_data.py
covidtracker/plot_geographical.py
covidtracker/plot_time_series.py
covidtracker/templates/92-160-g2016002-eng.pdf
covidtracker/templates/__init__.py
covidtracker/templates/lpr_000b16a_e.dbf
covidtracker/templates/lpr_000b16a_e.prj
covidtracker/templates/lpr_000b16a_e.shp
covidtracker/templates/lpr_000b16a_e.shx
covidtracker/templates/province_territory.html
covidtracker-0.1.3.dist-info/LICENSE
covidtracker-0.1.3.dist-info/WHEEL
covidtracker-0.1.3.dist-info/METADATA
covidtracker-0.1.3.dist-info/RECORD
